datacentertracesdatasets/__init__.py
datacentertracesdatasets/loadtraces.py
datacentertracesdatasets/alibaba2018/__init__.py
datacentertracesdatasets/alibaba2018/machine_usage_grouped_10_seconds.csv
datacentertracesdatasets/alibaba2018/machine_usage_grouped_300_seconds.csv
datacentertracesdatasets/alibaba2018/machine_usage_grouped_30_seconds.csv
datacentertracesdatasets/alibaba2018/synthetic_1_day_300_seconds/__init__.py
datacentertracesdatasets/azure_v2/__init__.py
datacentertracesdatasets/azure_v2/machine_usage_grouped_300_seconds.csv
datacentertracesdatasets/azure_v2/synthetic_1_day_300_seconds/__init__.py
datacentertracesdatasets/google2019/__init__.py
datacentertracesdatasets/google2019/machine_usage_grouped_300_seconds.csv
datacentertracesdatasets/google2019/machine_usage_grouped_300_seconds_percent.csv
datacentertracesdatasets/google2019/synthetic_1_day_300_seconds/__init__.py
datacentertracesdatasets-0.3.2.dist-info/LICENSE
datacentertracesdatasets-0.3.2.dist-info/METADATA
datacentertracesdatasets-0.3.2.dist-info/WHEEL
datacentertracesdatasets-0.3.2.dist-info/top_level.txt
datacentertracesdatasets-0.3.2.dist-info/RECORD
